hanzo_network/__init__.py
hanzo_network/distributed_network.py
hanzo_network/helpers.py
hanzo_network/local_compute.py
hanzo_network/local_network.py
hanzo_network/core/__init__.py
hanzo_network/core/agent.py
hanzo_network/core/network.py
hanzo_network/core/router.py
hanzo_network/core/state.py
hanzo_network/core/tool.py
hanzo_network/distributed/__init__.py
hanzo_network/distributed/discovery.py
hanzo_network/distributed/grpc_server.py
hanzo_network/distributed/minimal_discovery.py
hanzo_network/distributed/peer_handle.py
hanzo_network/distributed/server.py
hanzo_network/distributed/simplified_peer_handle.py
hanzo_network/distributed/udp_discovery.py
hanzo_network/distributed/grpc/__init__.py
hanzo_network/distributed/grpc/grpc_peer_handle.py
hanzo_network/distributed/grpc/grpc_server.py
hanzo_network/distributed/grpc/node_service.proto
hanzo_network/distributed/grpc/node_service_pb2.py
hanzo_network/distributed/grpc/node_service_pb2_grpc.py
hanzo_network/distributed/manual/__init__.py
hanzo_network/distributed/manual/manual_discovery.py
hanzo_network/distributed/manual/network_topology_config.py
hanzo_network/distributed/manual/test_manual_discovery.py
hanzo_network/distributed/manual/test_network_topology_config.py
hanzo_network/distributed/manual/test_data/invalid_config.json
hanzo_network/distributed/manual/test_data/invalid_json.json
hanzo_network/distributed/manual/test_data/test_config.json
hanzo_network/distributed/manual/test_data/test_config_single_node.json
hanzo_network/distributed/tailscale/__init__.py
hanzo_network/distributed/tailscale/tailscale_discovery.py
hanzo_network/distributed/tailscale/tailscale_helpers.py
hanzo_network/distributed/tailscale/test_tailscale_discovery.py
hanzo_network/distributed/udp/__init__.py
hanzo_network/distributed/udp/test_udp_discovery.py
hanzo_network/distributed/udp/udp_discovery.py
hanzo_network/download/__init__.py
hanzo_network/download/new_shard_download.py
hanzo_network/download/shard_download.py
hanzo_network-0.1.3.dist-info/METADATA
hanzo_network-0.1.3.dist-info/WHEEL
hanzo_network-0.1.3.dist-info/RECORD
